md_to_pdf/__init__.py
md_to_pdf/cli.py
md_to_pdf/core.py
md_to_pdf/types.py
md_to_pdf/utils/__init__.py
md_to_pdf/utils/system_utils.py
py_md_to_pdf-0.1.0.dist-info/METADATA
py_md_to_pdf-0.1.0.dist-info/WHEEL
py_md_to_pdf-0.1.0.dist-info/top_level.txt
py_md_to_pdf-0.1.0.dist-info/RECORD
